setup.py
asynckit/__init__.py
asynckit/errors.py
asynckit/pool.py
asynckit/value.py
asynckit/worker.py
asynckit.egg-info/PKG-INFO
asynckit.egg-info/SOURCES.txt
asynckit.egg-info/dependency_links.txt
asynckit.egg-info/top_level.txt
asynckit/test/__init__.py
asynckit/test/test_async_value_list.py
asynckit/test/test_pool.py
asynckit/test/test_value.py
asynckit/test/test_value_agregator.py
asynckit/test/test_value_chain.py
asynckit/test/test_worker.py