Metadata-Version: 1.1
Name: asynckit
Version: 0.4.2-r2702203
Summary: AsyncKit is a micro-toolkit for doing async work in python
Home-page: https://github.com/tbug/asynckit.py
Author: Henrik Tudborg
Author-email: henrik@tudb.org
License: MIT
Keywords: async utility util asynckit helper
Platform: UNKNOWN
Classifier: Development Status :: 4 - Beta
Classifier: Intended Audience :: Developers
Classifier: License :: OSI Approved :: MIT License
Classifier: Operating System :: MacOS
Classifier: Operating System :: POSIX
